{"assets/icons/Arhive_light.svg":["assets/icons/Arhive_light.svg"],"assets/icons/Bag_alt_light.svg":["assets/icons/Bag_alt_light.svg"],"assets/icons/Calendar_light.svg":["assets/icons/Calendar_light.svg"],"assets/icons/Create%20Order%20Button.svg":["assets/icons/Create%20Order%20Button.svg"],"assets/icons/Currency.svg":["assets/icons/Currency.svg"],"assets/icons/List%20Icon.svg":["assets/icons/List%20Icon.svg"],"assets/icons/Message%20Icon.svg":["assets/icons/Message%20Icon.svg"],"assets/icons/Pin_alt_light.svg":["assets/icons/Pin_alt_light.svg"],"assets/icons/Time_light.svg":["assets/icons/Time_light.svg"],"assets/icons/User_alt_light.svg":["assets/icons/User_alt_light.svg"],"packages/cupertino_icons/assets/CupertinoIcons.ttf":["packages/cupertino_icons/assets/CupertinoIcons.ttf"]}